qcconst/__init__.py
qcconst/constants.py
qcconst/constants.pyi
qcconst/models.py
qcconst/periodic_table.py
qcconst/py.typed
qcconst/solvents.py
qcconst/utils.py
qcconst/data/codata2022.csv
qcconst/data/constants.csv
qcconst/data/covalent_radii_cordero_2008.csv
qcconst/data/covalent_radii_pyykko_2009.csv
qcconst/data/group_period.csv
qcconst/data/pubchem.csv
qcconst/data/solvents.csv
qcconst/data/vdw_radii_alvarez_2013.csv
qcconst-0.2.1.dist-info/METADATA
qcconst-0.2.1.dist-info/WHEEL
qcconst-0.2.1.dist-info/licenses/LICENSE
qcconst-0.2.1.dist-info/RECORD
