Metadata-Version: 2.4
Name: qcconst
Version: 0.2.1
Summary: Physical constants, conversion factors, and a periodic table with clear source information for every value.
Project-URL: Homepage, https://github.com/coltonbh/qcconst
Project-URL: Documentation, https://github.com/coltonbh/qcconst#readme
Project-URL: Source, https://github.com/coltonbh/qcconst
Project-URL: Changelog, https://github.com/coltonbh/qcconst/blob/master/CHANGELOG.md
Project-URL: Bug Tracker, https://github.com/coltonbh/qcconst/issues
Author-email: Colton Hicks <github@coltonhicks.com>
License: The MIT License (MIT)
License-File: LICENSE
Keywords: chemistry,constants,conversion factors,periodic table,physics,scientific computing
Classifier: Development Status :: 4 - Beta
Classifier: Intended Audience :: Developers
Classifier: Intended Audience :: Science/Research
Classifier: License :: OSI Approved :: MIT License
Classifier: Operating System :: OS Independent
Classifier: Programming Language :: Python :: 3.9
Classifier: Programming Language :: Python :: 3.10
Classifier: Programming Language :: Python :: 3.11
Classifier: Programming Language :: Python :: 3.12
Classifier: Programming Language :: Python :: 3.13
Classifier: Topic :: Scientific/Engineering
Classifier: Topic :: Software Development :: Libraries
Requires-Python: >=3.9
